allauth_themes/bootstrap/__init__.py
allauth_themes/bootstrap/apps.py
allauth_themes/bootstrap/templates/allauth/429.html
allauth_themes/bootstrap/templates/allauth/elements/alert.html
allauth_themes/bootstrap/templates/allauth/elements/badge.html
allauth_themes/bootstrap/templates/allauth/elements/button.html
allauth_themes/bootstrap/templates/allauth/elements/button__entrance.html
allauth_themes/bootstrap/templates/allauth/elements/field.html
allauth_themes/bootstrap/templates/allauth/elements/fields.html
allauth_themes/bootstrap/templates/allauth/elements/form.html
allauth_themes/bootstrap/templates/allauth/elements/form__entrance.html
allauth_themes/bootstrap/templates/allauth/elements/h1.html
allauth_themes/bootstrap/templates/allauth/elements/h1__entrance.html
allauth_themes/bootstrap/templates/allauth/elements/h2__entrance.html
allauth_themes/bootstrap/templates/allauth/elements/h2__manage.html
allauth_themes/bootstrap/templates/allauth/elements/hr.html
allauth_themes/bootstrap/templates/allauth/elements/img.html
allauth_themes/bootstrap/templates/allauth/elements/panel.html
allauth_themes/bootstrap/templates/allauth/elements/provider.html
allauth_themes/bootstrap/templates/allauth/elements/provider_list.html
allauth_themes/bootstrap/templates/allauth/elements/table.html
allauth_themes/bootstrap/templates/allauth/layouts/base.html
allauth_themes/bootstrap/templates/allauth/layouts/css.html
allauth_themes/bootstrap/templates/allauth/layouts/entrance.html
allauth_themes/bootstrap/templates/allauth/layouts/manage.html
allauth_themes/bootstrap/templates/allauth/layouts/messages.html
django_allauth_themes-0.1.2.dist-info/LICENSE
django_allauth_themes-0.1.2.dist-info/METADATA
django_allauth_themes-0.1.2.dist-info/WHEEL
django_allauth_themes-0.1.2.dist-info/top_level.txt
django_allauth_themes-0.1.2.dist-info/RECORD
