Metadata-Version: 2.1
Name: django-allauth-themes
Version: 0.1.2
Summary: Themes for Django-Allauth
Author-email: harrelchris <harrelchris+pypi@gmail.com>
License: MIT License
Project-URL: Homepage, https://github.com/harrelchris/django-allauth-themes
Project-URL: Issues, https://github.com/harrelchris/django-allauth-themes/issues
Requires-Python: >=3.7
License-File: LICENSE
Requires-Dist: django-allauth
